embuild/__init__.py
embuild/__main__.py
embuild/embuild.py
embuild-1.1.0.dist-info/LICENSE
embuild-1.1.0.dist-info/METADATA
embuild-1.1.0.dist-info/WHEEL
embuild-1.1.0.dist-info/entry_points.txt
embuild-1.1.0.dist-info/top_level.txt
embuild-1.1.0.dist-info/RECORD
