Metadata-Version: 2.1
Name: embuild
Version: 1.1.0
Summary: Embuild is a tool for C/CMake static library management
Author-email: Grzegorz Grzęda <grzegorz.grzeda@g2labs.pl>
Project-URL: Homepage, https://github.com/g2labs-grzegorz-grzeda/embuild
Project-URL: Issues, https://github.com/g2labs-grzegorz-grzeda/embuild/issues
Project-URL: Library index, https://embuild.dev
Classifier: Programming Language :: Python :: 3
Classifier: License :: OSI Approved :: MIT License
Classifier: Operating System :: OS Independent
Requires-Python: >=3.8
License-File: LICENSE
Requires-Dist: vt100logging >=1.1.0
